[
  {
    "_id": "1234",
    "name": "React JS",
    "number": "CS1234",
    "startDate": "2023-01-10",
    "endDate": "2023-05-15",
    "department": "CS",
    "image": "/images/reactjs.jpg",
    "credits": 4,
    "description": "Learn to build dynamic, component-based web applications using React JS, managing state, props, and hooks effectively."
  },
  {
    "_id": "2345",
    "name": "Node JS",
    "number": "CS2345",
    "startDate": "2023-01-10",
    "endDate": "2023-05-15",
    "department": "CS",
    "image": "/images/nodejs.jpg",
    "credits": 4,
    "description": "Master backend development with Node JS, creating servers, REST APIs, and connecting applications to databases."
  },
  {
    "_id": "3456",
    "name": "HTML",
    "number": "CS3456",
    "startDate": "2023-01-10",
    "endDate": "2023-05-15",
    "department": "CS",
    "image": "/images/html.jpg",
    "credits": 4,
    "description": "Understand the structure of web pages and build semantic HTML layouts for modern web applications."
  },
  {
    "_id": "4567",
    "name": "CSS",
    "number": "CS4567",
    "startDate": "2023-01-10",
    "endDate": "2023-05-15",
    "department": "CS",
    "image": "/images/CSS.jpg",
    "credits": 4,
    "description": "Design visually appealing and responsive web pages using advanced CSS techniques including Flexbox, Grid, and animations."
  },
  {
    "_id": "5678",
    "name": "JavaScript",
    "number": "CS5678",
    "startDate": "2023-01-10",
    "endDate": "2023-05-15",
    "department": "CS",
    "image": "/images/js.jpg",
    "credits": 4,
    "description": "Gain expertise in core JavaScript concepts, DOM manipulation, event handling, and creating interactive web experiences."
  },
  {
    "_id": "6789",
    "name": "NextJS",
    "number": "CS6789",
    "startDate": "2023-01-10",
    "endDate": "2023-05-15",
    "department": "CS",
    "image": "/images/next.jpg",
    "credits": 4,
    "description": "Learn server-side rendering, static site generation, and modern web application development using the Next.js framework."
  },
  {
    "_id": "7890",
    "name": "MongoDB",
    "number": "CS7890",
    "startDate": "2023-01-10",
    "endDate": "2023-05-15",
    "department": "CS",
    "image": "/images/mongo.jpg",
    "credits": 4,
    "description": "Master MongoDB database design, CRUD operations, aggregation, and building scalable applications with NoSQL."
  }
]
